teams_ai_azml/__init__.py
teams_ai_azml/activity_type.py
teams_ai_azml/adaptive_cards/__init__.py
teams_ai_azml/adaptive_cards/adaptive_cards.py
teams_ai_azml/adaptive_cards/adaptive_cards_options.py
teams_ai_azml/adaptive_cards/adaptive_cards_search_params.py
teams_ai_azml/adaptive_cards/adaptive_cards_search_result.py
teams_ai_azml/ai/__init__.py
teams_ai_azml/ai/actions/__init__.py
teams_ai_azml/ai/actions/action_entry.py
teams_ai_azml/ai/actions/action_turn_context.py
teams_ai_azml/ai/actions/action_types.py
teams_ai_azml/ai/ai.py
teams_ai_azml/ai/ai_options.py
teams_ai_azml/ai/augmentations/__init__.py
teams_ai_azml/ai/augmentations/augmentation.py
teams_ai_azml/ai/augmentations/default_augmentation.py
teams_ai_azml/ai/augmentations/monologue_augmentation.py
teams_ai_azml/ai/augmentations/sequence_augmentation.py
teams_ai_azml/ai/citations/__init__.py
teams_ai_azml/ai/citations/citations.py
teams_ai_azml/ai/clients/__init__.py
teams_ai_azml/ai/clients/llm_client.py
teams_ai_azml/ai/data_sources/__init__.py
teams_ai_azml/ai/data_sources/data_source.py
teams_ai_azml/ai/data_sources/text_data_source.py
teams_ai_azml/ai/embeddings/__init__.py
teams_ai_azml/ai/embeddings/azure_openai_embeddings.py
teams_ai_azml/ai/embeddings/azure_openai_embeddings_options.py
teams_ai_azml/ai/embeddings/embeddings_model.py
teams_ai_azml/ai/embeddings/embeddings_response.py
teams_ai_azml/ai/embeddings/openai_embeddings.py
teams_ai_azml/ai/embeddings/openai_embeddings_options.py
teams_ai_azml/ai/models/__init__.py
teams_ai_azml/ai/models/chat_completion_action.py
teams_ai_azml/ai/models/openai_model.py
teams_ai_azml/ai/models/prompt_completion_model.py
teams_ai_azml/ai/models/prompt_response.py
teams_ai_azml/ai/moderators/__init__.py
teams_ai_azml/ai/moderators/azure_content_safety_moderator.py
teams_ai_azml/ai/moderators/default_moderator.py
teams_ai_azml/ai/moderators/moderator.py
teams_ai_azml/ai/moderators/openai_moderator.py
teams_ai_azml/ai/planners/__init__.py
teams_ai_azml-1.1.2.dist-info/LICENSE
teams_ai_azml-1.1.2.dist-info/METADATA
teams_ai_azml-1.1.2.dist-info/WHEEL
teams_ai_azml-1.1.2.dist-info/entry_points.txt
teams_ai_azml-1.1.2.dist-info/RECORD
